ipgogogo/__init__.py
ipgogogo/run.py
ipgogogo/ui.py
ipgogogo/core/__init__.py
ipgogogo/core/core.py
ipgogogo/core/rcore.py
ipgogogo/core/wcore.py
ipgogogo/model/__init__.py
ipgogogo/model/state.py
ipgogogo/utils/__init__.py
ipgogogo/utils/checkdir.py
ipgogogo/utils/logger.py
ipgogogo-1.1.1.dist-info/LICENSE
ipgogogo-1.1.1.dist-info/METADATA
ipgogogo-1.1.1.dist-info/WHEEL
ipgogogo-1.1.1.dist-info/top_level.txt
ipgogogo-1.1.1.dist-info/RECORD
